binarytostring/__init__.py
binarytostring-0.1.dist-info/METADATA
binarytostring-0.1.dist-info/WHEEL
binarytostring-0.1.dist-info/top_level.txt
binarytostring-0.1.dist-info/RECORD
