Metadata-Version: 2.1
Name: binarytostring
Version: 0.1
Summary: change string to binary
Home-page: UNKNOWN
Author: adityasg
Author-email: aditya.tiwari@sganalytics.com
License: MIT
Platform: UNKNOWN
